{"cameraMode":{"drawMode":0,"name":"Shaded","section":"Shading Mode"},"sceneLighting":true,"audioPlay":false,"sceneViewState":{"m_AlwaysRefresh":false,"showFog":true,"showSkybox":true,"showFlares":true,"showImageEffects":true,"showParticleSystems":true,"showVisualEffectGraphs":true,"m_FxEnabled":true},"in2DMode":false,"pivot":{"x":111.114013671875,"y":17.831695556640626,"z":40.430049896240237},"rotation":{"x":0.1885872483253479,"y":0.040763236582279208,"z":-0.028109265491366388,"w":0.9824137687683106},"size":9.548819541931153,"orthographic":false}